{
"meta":{"test_sets":[],"test_metrics":[],"learn_metrics":[{"best_value":"Min","name":"Logloss"}],"launch_mode":"Train","parameters":"","iteration_count":100,"learn_sets":["learn"],"name":"experiment"},
"iterations":[
{"learn":[0.6877416298],"iteration":0,"passed_time":0.01179449725,"remaining_time":1.167655228},
{"learn":[0.6830512547],"iteration":1,"passed_time":0.02357493094,"remaining_time":1.155171616},
{"learn":[0.6786893459],"iteration":2,"passed_time":0.0347975055,"remaining_time":1.125119345},
{"learn":[0.6746899033],"iteration":3,"passed_time":0.04584084464,"remaining_time":1.100180271},
{"learn":[0.6710087745],"iteration":4,"passed_time":0.05769451195,"remaining_time":1.096195727},
{"learn":[0.6673126978],"iteration":5,"passed_time":0.0689313993,"remaining_time":1.079925256},
{"learn":[0.6639173947],"iteration":6,"passed_time":0.07997543286,"remaining_time":1.062530751},
{"learn":[0.6608892669],"iteration":7,"passed_time":0.09104273338,"remaining_time":1.046991434},
{"learn":[0.6579967076],"iteration":8,"passed_time":0.1023743089,"remaining_time":1.035118012},
{"learn":[0.6552344462],"iteration":9,"passed_time":0.1132492402,"remaining_time":1.019243161},
{"learn":[0.65286904],"iteration":10,"passed_time":0.1241435342,"remaining_time":1.00443405},
{"learn":[0.6504297149],"iteration":11,"passed_time":0.1350691227,"remaining_time":0.9905069},
{"learn":[0.6481322657],"iteration":12,"passed_time":0.1457878386,"remaining_time":0.975657074},
{"learn":[0.6455384496],"iteration":13,"passed_time":0.1567571417,"remaining_time":0.9629367277},
{"learn":[0.6436731952],"iteration":14,"passed_time":0.1677446355,"remaining_time":0.9505529347},
{"learn":[0.6417745886],"iteration":15,"passed_time":0.1786733297,"remaining_time":0.9380349807},
{"learn":[0.6397235648],"iteration":16,"passed_time":0.1899134306,"remaining_time":0.9272243966},
{"learn":[0.6382711504],"iteration":17,"passed_time":0.2018742972,"remaining_time":0.9196495763},
{"learn":[0.6363263607],"iteration":18,"passed_time":0.2128488085,"remaining_time":0.9074080782},
{"learn":[0.6347929855],"iteration":19,"passed_time":0.2241839733,"remaining_time":0.8967358933},
{"learn":[0.6334001902],"iteration":20,"passed_time":0.2359242703,"remaining_time":0.8875246358},
{"learn":[0.6316761637],"iteration":21,"passed_time":0.2473031219,"remaining_time":0.8768019777},
{"learn":[0.6304285709],"iteration":22,"passed_time":0.2587642463,"remaining_time":0.866297694},
{"learn":[0.6290373308],"iteration":23,"passed_time":0.2701459836,"remaining_time":0.8554622814},
{"learn":[0.6276419002],"iteration":24,"passed_time":0.2775213926,"remaining_time":0.8325641779},
{"learn":[0.6260893],"iteration":25,"passed_time":0.2845530911,"remaining_time":0.8098818748},
{"learn":[0.6244643793],"iteration":26,"passed_time":0.2916841667,"remaining_time":0.7886275617},
{"learn":[0.6231831752],"iteration":27,"passed_time":0.2985656403,"remaining_time":0.7677402179},
{"learn":[0.6221296035],"iteration":28,"passed_time":0.3054293445,"remaining_time":0.7477752917},
{"learn":[0.6210312742],"iteration":29,"passed_time":0.3122433328,"remaining_time":0.7285677766},
{"learn":[0.6199564902],"iteration":30,"passed_time":0.3192542573,"remaining_time":0.7105981857},
{"learn":[0.6183784439],"iteration":31,"passed_time":0.3261304264,"remaining_time":0.6930271561},
{"learn":[0.6172424424],"iteration":32,"passed_time":0.3336161195,"remaining_time":0.6773418183},
{"learn":[0.6162099101],"iteration":33,"passed_time":0.3401717755,"remaining_time":0.6603334466},
{"learn":[0.6152202344],"iteration":34,"passed_time":0.3470328355,"remaining_time":0.6444895516},
{"learn":[0.6143230546],"iteration":35,"passed_time":0.3540289148,"remaining_time":0.6293847375},
{"learn":[0.6134353792],"iteration":36,"passed_time":0.3607222259,"remaining_time":0.614202709},
{"learn":[0.6121066959],"iteration":37,"passed_time":0.3676698925,"remaining_time":0.5998824562},
{"learn":[0.6108399646],"iteration":38,"passed_time":0.3746234509,"remaining_time":0.5859495002},
{"learn":[0.6099144441],"iteration":39,"passed_time":0.3819319919,"remaining_time":0.5728979878},
{"learn":[0.6089790736],"iteration":40,"passed_time":0.3888537635,"remaining_time":0.55957005},
{"learn":[0.6080395124],"iteration":41,"passed_time":0.3957522737,"remaining_time":0.5465150446},
{"learn":[0.6072436849],"iteration":42,"passed_time":0.4025575292,"remaining_time":0.5336227713},
{"learn":[0.606041152],"iteration":43,"passed_time":0.4094879665,"remaining_time":0.5211665028},
{"learn":[0.6050634433],"iteration":44,"passed_time":0.4160837971,"remaining_time":0.5085468631},
{"learn":[0.60431894],"iteration":45,"passed_time":0.422935869,"remaining_time":0.4964899331},
{"learn":[0.6034450893],"iteration":46,"passed_time":0.4298545937,"remaining_time":0.4847296482},
{"learn":[0.6023558758],"iteration":47,"passed_time":0.4368984492,"remaining_time":0.4733066533},
{"learn":[0.6016965672],"iteration":48,"passed_time":0.4439090218,"remaining_time":0.4620277574},
{"learn":[0.6008030595],"iteration":49,"passed_time":0.4506889187,"remaining_time":0.4506889187},
{"learn":[0.6000914331],"iteration":50,"passed_time":0.4580334885,"remaining_time":0.4400713909},
{"learn":[0.5991738186],"iteration":51,"passed_time":0.4656611876,"remaining_time":0.4298410962},
{"learn":[0.5984439609],"iteration":52,"passed_time":0.4728330673,"remaining_time":0.4193047955},
{"learn":[0.5975487684],"iteration":53,"passed_time":0.479943037,"remaining_time":0.4088403649},
{"learn":[0.5967773069],"iteration":54,"passed_time":0.4867739013,"remaining_time":0.3982695556},
{"learn":[0.5962323545],"iteration":55,"passed_time":0.4936021383,"remaining_time":0.3878302515},
{"learn":[0.5955302325],"iteration":56,"passed_time":0.5001036843,"remaining_time":0.3772712004},
{"learn":[0.5948000292],"iteration":57,"passed_time":0.5068488709,"remaining_time":0.3670284927},
{"learn":[0.5939876552],"iteration":58,"passed_time":0.5132637671,"remaining_time":0.3566748212},
{"learn":[0.5934412772],"iteration":59,"passed_time":0.5202931123,"remaining_time":0.3468620748},
{"learn":[0.5928755877],"iteration":60,"passed_time":0.5276070388,"remaining_time":0.337322533},
{"learn":[0.5920261031],"iteration":61,"passed_time":0.5351043071,"remaining_time":0.327967156},
{"learn":[0.5915575754],"iteration":62,"passed_time":0.5423160466,"remaining_time":0.318503075},
{"learn":[0.5910590653],"iteration":63,"passed_time":0.5495562727,"remaining_time":0.3091254034},
{"learn":[0.5904421381],"iteration":64,"passed_time":0.5572814222,"remaining_time":0.3000746119},
{"learn":[0.5895254309],"iteration":65,"passed_time":0.5647965024,"remaining_time":0.2909557739},
{"learn":[0.58885152],"iteration":66,"passed_time":0.5716560269,"remaining_time":0.2815619237},
{"learn":[0.5880040226],"iteration":67,"passed_time":0.5787531476,"remaining_time":0.2723544224},
{"learn":[0.5874875837],"iteration":68,"passed_time":0.5854707348,"remaining_time":0.2630375765},
{"learn":[0.5869657445],"iteration":69,"passed_time":0.5925774609,"remaining_time":0.2539617689},
{"learn":[0.5864399738],"iteration":70,"passed_time":0.5993225919,"remaining_time":0.2447937347},
{"learn":[0.5859379644],"iteration":71,"passed_time":0.6065060985,"remaining_time":0.2358634828},
{"learn":[0.5854324556],"iteration":72,"passed_time":0.6136717817,"remaining_time":0.2269744946},
{"learn":[0.5848678462],"iteration":73,"passed_time":0.6204637453,"remaining_time":0.2180007754},
{"learn":[0.5844316769],"iteration":74,"passed_time":0.627246267,"remaining_time":0.209082089},
{"learn":[0.5838431335],"iteration":75,"passed_time":0.6341969868,"remaining_time":0.2002727327},
{"learn":[0.5833931396],"iteration":76,"passed_time":0.6416492705,"remaining_time":0.1916614704},
{"learn":[0.5828760094],"iteration":77,"passed_time":0.6486163655,"remaining_time":0.1829430775},
{"learn":[0.5822810721],"iteration":78,"passed_time":0.6555223005,"remaining_time":0.1742527634},
{"learn":[0.5817595352],"iteration":79,"passed_time":0.6622104444,"remaining_time":0.1655526111},
{"learn":[0.5811325419],"iteration":80,"passed_time":0.6691082269,"remaining_time":0.1569513125},
{"learn":[0.5806562378],"iteration":81,"passed_time":0.6759742666,"remaining_time":0.1483845951},
{"learn":[0.5801712068],"iteration":82,"passed_time":0.6829815277,"remaining_time":0.1398877828},
{"learn":[0.5797297669],"iteration":83,"passed_time":0.6898590401,"remaining_time":0.1314017219},
{"learn":[0.5793957275],"iteration":84,"passed_time":0.696584195,"remaining_time":0.1229266226},
{"learn":[0.5789685011],"iteration":85,"passed_time":0.7036226332,"remaining_time":0.1145432194},
{"learn":[0.578688983],"iteration":86,"passed_time":0.7105556645,"remaining_time":0.1061749844},
{"learn":[0.5782039952],"iteration":87,"passed_time":0.7174696625,"remaining_time":0.09783677216},
{"learn":[0.5776937342],"iteration":88,"passed_time":0.7247443026,"remaining_time":0.08957513853},
{"learn":[0.5771991555],"iteration":89,"passed_time":0.732035206,"remaining_time":0.08133724512},
{"learn":[0.5766438346],"iteration":90,"passed_time":0.7392548503,"remaining_time":0.07311311706},
{"learn":[0.5761375914],"iteration":91,"passed_time":0.746127967,"remaining_time":0.06488069278},
{"learn":[0.5756896279],"iteration":92,"passed_time":0.7527411218,"remaining_time":0.0566579339},
{"learn":[0.5752619262],"iteration":93,"passed_time":0.7597105624,"remaining_time":0.04849216356},
{"learn":[0.5747209484],"iteration":94,"passed_time":0.7669641947,"remaining_time":0.04036653656},
{"learn":[0.574167658],"iteration":95,"passed_time":0.7736913773,"remaining_time":0.03223714072},
{"learn":[0.5738130113],"iteration":96,"passed_time":0.7810233658,"remaining_time":0.02415536183},
{"learn":[0.5732359164],"iteration":97,"passed_time":0.7878916369,"remaining_time":0.01607942116},
{"learn":[0.5727744739],"iteration":98,"passed_time":0.794857806,"remaining_time":0.008028866728},
{"learn":[0.5724358119],"iteration":99,"passed_time":0.8018734202,"remaining_time":0}
]}